aifrenz/__init__.py
aifrenz-0.0.1.dist-info/LICENSE
aifrenz-0.0.1.dist-info/METADATA
aifrenz-0.0.1.dist-info/WHEEL
aifrenz-0.0.1.dist-info/top_level.txt
aifrenz-0.0.1.dist-info/RECORD
